ai/__init__.py
ai/config.py
ai/blocks/__init__.py
ai/dataset/__init__.py
ai/dataset/augment.py
ai/llm/__init__.py
ai/llm/postprocess.py
ai/optim/__init__.py
ai/tensor/__init__.py
ai/trainer/__init__.py
ai/utils/__init__.py
tests/__init__.py
tests/test_config.py
ai-1.2.dist-info/METADATA
ai-1.2.dist-info/WHEEL
ai-1.2.dist-info/top_level.txt
ai-1.2.dist-info/RECORD
