Metadata-Version: 2.4
Name: ai
Version: 1.2
Summary: Ai lib.
Home-page: https://github.com/Decalogue/ai
Author: Decalogue
Author-email: Decalogue <decalogue80@gmail.com>
License: MIT
Project-URL: Homepage, https://github.com/Decalogue/ai
Classifier: Development Status :: 4 - Beta
Classifier: Environment :: Console
Classifier: Intended Audience :: Developers
Classifier: Intended Audience :: Information Technology
Classifier: Natural Language :: English
Classifier: Natural Language :: Chinese (Simplified)
Classifier: License :: OSI Approved :: MIT License
Classifier: Operating System :: Microsoft :: Windows
Classifier: Operating System :: POSIX :: Linux
Classifier: Operating System :: MacOS :: MacOS X
Classifier: Operating System :: Other OS
Classifier: Programming Language :: Python :: 3.10
Classifier: Programming Language :: Python :: 3.11
Classifier: Programming Language :: Python :: 3.12
Requires-Python: >=3.10
Dynamic: author
Dynamic: home-page
Dynamic: requires-python
